krdict/__init__.py
krdict/main.py
krdict/main.pyi
krdict/request.py
krdict/request.pyi
krdict/response.py
krdict/response.pyi
krdict/scraper/__init__.py
krdict/scraper/constants.py
krdict/scraper/main.py
krdict/scraper/main.pyi
krdict/scraper/request.py
krdict/scraper/response.py
krdict/types/__init__.py
krdict/types/exceptions.py
krdict/types/exceptions.pyi
krdict/types/main.py
krdict/types/scraper.py
krdict/types/enums/__init__.py
krdict/types/enums/base.py
krdict/types/enums/base.pyi
krdict/types/enums/semantic_category.py
krdict/types/enums/subject_category.py
krdict.py-3.0.2.dist-info/LICENSE
krdict.py-3.0.2.dist-info/METADATA
krdict.py-3.0.2.dist-info/WHEEL
krdict.py-3.0.2.dist-info/top_level.txt
krdict.py-3.0.2.dist-info/RECORD
