Metadata-Version: 2.1
Name: krdict.py
Version: 3.0.2
Summary: A package that helps with querying the Korean Learners' Dictionary API.
Home-page: https://github.com/omarkmu/krdict.py#readme
Author: Omar M.
Author-email: omarkmu@gmail.com
Project-URL: Source Code, https://github.com/omarkmu/krdict.py
Project-URL: Bug Tracker, https://github.com/omarkmu/krdict.py/issues
Project-URL: Documentation, https://krdictpy.readthedocs.io/en/v3.0.2
Keywords: korean dictionary api
Classifier: Development Status :: 5 - Production/Stable
Classifier: Programming Language :: Python :: 3
Classifier: License :: OSI Approved :: MIT License
Classifier: Operating System :: OS Independent
Requires-Python: >=3.8
License-File: LICENSE
